<annotation>
	<folder>Pin_detection</folder>
	<filename>000150.jpg</filename>
	<size>
		<width>847</width>
		<height>847</height>
		<depth>3</depth>
	</size>
		<segmented>0</segmented>
	<object>
		<name>slope</name>
		<pose>Unspecified</pose>
		<truncated>1</truncated>
		<difficult>0</difficult>
		<bndbox>
			<xmin>261.8947368421052</xmin>
			<ymin>427.9473684210526</ymin>
			<xmax>561.8947368421052</xmax>
			<ymax>661.2807017543859</ymax>
		</bndbox>
	</object>
	<object>
		<name>slope</name>
		<pose>Unspecified</pose>
		<truncated>1</truncated>
		<difficult>0</difficult>
		<bndbox>
			<xmin>216.28070175438592</xmin>
			<ymin>658.6491228070174</ymin>
			<xmax>381.19298245614027</xmax>
			<ymax>841.9824561403508</ymax>
		</bndbox>
	</object>
</annotation>